bivital/__init__.py
bivital/bvtool.py
bivital/firmware.py
bivital/monitor.py
bivital/pipeline.py
bivital/processing.py
bivital/serial_connect.py
bivital/storage.py
bivital/example/__init__.py
bivital/example/basic_example.ipynb
bivital/example/interpolation_example.ipynb
bivital/example/label_handling_example.ipynb
bivital/example/time_index_handling_example.ipynb
bivital/example/example_project/__init__.py
bivital/example/example_project/config.ini
bivital/example/example_project/history.txt
bivital/example/example_project/Workout_series/0D99/log00.csv
bivital/example/example_project/Workout_series/0D99/log01.csv
bivital/example/example_project/Workout_series/4A13/log00.csv
bivital/example/example_project/Workout_series/Label/label.csv
bivital-0.1.7.dist-info/licenses/LICENSE
bivital-0.1.7.dist-info/METADATA
bivital-0.1.7.dist-info/WHEEL
bivital-0.1.7.dist-info/entry_points.txt
bivital-0.1.7.dist-info/top_level.txt
bivital-0.1.7.dist-info/RECORD
