Metadata-Version: 2.4
Name: bivital
Version: 0.1.7
Summary: BiVital Library
Author-email: University Bielefeld <ks-bivital-support@techfak.uni-bielefeld.de>
License: MIT
Project-URL: Homepage, https://bivital.eu/
Project-URL: Repository, https://gitlab.ub.uni-bielefeld.de/bi-vital-open-source/py_bivital.git
Project-URL: Issues, https://gitlab.ub.uni-bielefeld.de/bi-vital-open-source/py_bivital/-/issues
Classifier: Programming Language :: Python :: 3
Classifier: Programming Language :: Python :: 3 :: Only
Classifier: Programming Language :: Python :: 3.10
Classifier: Programming Language :: Python :: 3.11
Classifier: Programming Language :: Python :: 3.12
Classifier: License :: OSI Approved :: MIT License
Classifier: Operating System :: OS Independent
Requires-Python: >=3.10
License-File: LICENSE
Requires-Dist: pandas<3.0,>=2.2
Requires-Dist: pyserial<4.0,>=3.5
Requires-Dist: matplotlib<4.0,>=3.10
Requires-Dist: usb-monitor<2.0,>=1.23
Requires-Dist: requests<3.0,>=2.32.4
Provides-Extra: notebook
Requires-Dist: jupyterlab<5,>=4; extra == "notebook"
Requires-Dist: ipykernel>=6; extra == "notebook"
Dynamic: license-file
